instant_segment-0.1.9.dist-info/METADATA
instant_segment-0.1.9.dist-info/WHEEL
instant_segment-0.1.9.dist-info/licenses/LICENSE
instant_segment/__init__.py
instant_segment/instant_segment.cpython-39-darwin.so
instant_segment-0.1.9.dist-info/RECORD
