Metadata-Version: 2.4
Name: instant-segment
Version: 0.1.9
License-File: LICENSE
Summary: Fast English word segmentation
Home-Page: https://github.com/InstantDomain/instant-segment
License: Apache-2.0
Project-URL: Source Code, https://github.com/InstantDomain/instant-segment
